{
"meta":{"test_sets":[],"test_metrics":[],"learn_metrics":[{"best_value":"Min","name":"RMSE"}],"launch_mode":"Train","parameters":"","iteration_count":100,"learn_sets":["learn"],"name":"experiment"},
"iterations":[
{"learn":[14.14522824],"iteration":0,"passed_time":0.04602370876,"remaining_time":4.556347167},
{"learn":[13.36899529],"iteration":1,"passed_time":0.04626300561,"remaining_time":2.266887275},
{"learn":[12.68852399],"iteration":2,"passed_time":0.046430842,"remaining_time":1.501263891},
{"learn":[11.99834794],"iteration":3,"passed_time":0.04656353424,"remaining_time":1.117524822},
{"learn":[11.42648001],"iteration":4,"passed_time":0.04669961266,"remaining_time":0.8872926404},
{"learn":[10.87196111],"iteration":5,"passed_time":0.04683923755,"remaining_time":0.7338147216},
{"learn":[10.4216325],"iteration":6,"passed_time":0.04698980241,"remaining_time":0.6242930892},
{"learn":[9.939092041],"iteration":7,"passed_time":0.0471408181,"remaining_time":0.5421194081},
{"learn":[9.53453716],"iteration":8,"passed_time":0.0472854321,"remaining_time":0.4781082579},
{"learn":[9.124892438],"iteration":9,"passed_time":0.04741185289,"remaining_time":0.426706676},
{"learn":[8.819588196],"iteration":10,"passed_time":0.04753626,"remaining_time":0.3846115582},
{"learn":[8.516574859],"iteration":11,"passed_time":0.04765150038,"remaining_time":0.3494443361},
{"learn":[8.217364689],"iteration":12,"passed_time":0.04778897134,"remaining_time":0.3198185005},
{"learn":[7.977075551],"iteration":13,"passed_time":0.0479133484,"remaining_time":0.2943248544},
{"learn":[7.750156635],"iteration":14,"passed_time":0.04803410885,"remaining_time":0.2721932835},
{"learn":[7.570922032],"iteration":15,"passed_time":0.04816135114,"remaining_time":0.2528470935},
{"learn":[7.394449967],"iteration":16,"passed_time":0.04829304155,"remaining_time":0.2357836734},
{"learn":[7.217944252],"iteration":17,"passed_time":0.04841849056,"remaining_time":0.2205731237},
{"learn":[7.06406552],"iteration":18,"passed_time":0.04854863815,"remaining_time":0.20697051},
{"learn":[6.922069841],"iteration":19,"passed_time":0.04867115181,"remaining_time":0.1946846072},
{"learn":[6.794695098],"iteration":20,"passed_time":0.04879824382,"remaining_time":0.1835743458},
{"learn":[6.688838881],"iteration":21,"passed_time":0.04893449255,"remaining_time":0.173495019},
{"learn":[6.594681291],"iteration":22,"passed_time":0.04906082317,"remaining_time":0.1642471037},
{"learn":[6.492701396],"iteration":23,"passed_time":0.04917847796,"remaining_time":0.1557318469},
{"learn":[6.395911952],"iteration":24,"passed_time":0.04929726481,"remaining_time":0.1478917944},
{"learn":[6.316254063],"iteration":25,"passed_time":0.04942230307,"remaining_time":0.140663478},
{"learn":[6.253731974],"iteration":26,"passed_time":0.04954260269,"remaining_time":0.1339485184},
{"learn":[6.192621935],"iteration":27,"passed_time":0.0496696947,"remaining_time":0.1277220721},
{"learn":[6.132570051],"iteration":28,"passed_time":0.04981005093,"remaining_time":0.1219487454},
{"learn":[6.078204866],"iteration":29,"passed_time":0.04993259464,"remaining_time":0.1165093875},
{"learn":[6.022393462],"iteration":30,"passed_time":0.05004780496,"remaining_time":0.1113967272},
{"learn":[5.975750116],"iteration":31,"passed_time":0.05015990961,"remaining_time":0.1065898079},
{"learn":[5.935737001],"iteration":32,"passed_time":0.05027731394,"remaining_time":0.1020781829},
{"learn":[5.894267675],"iteration":33,"passed_time":0.05040397517,"remaining_time":0.09784301062},
{"learn":[5.863525006],"iteration":34,"passed_time":0.05052217094,"remaining_time":0.09382688889},
{"learn":[5.833461311],"iteration":35,"passed_time":0.05065371107,"remaining_time":0.09005104191},
{"learn":[5.806880349],"iteration":36,"passed_time":0.05077711636,"remaining_time":0.08645833326},
{"learn":[5.779186938],"iteration":37,"passed_time":0.0509061419,"remaining_time":0.08305738942},
{"learn":[5.752000272],"iteration":38,"passed_time":0.0510465382,"remaining_time":0.07984202129},
{"learn":[5.719092953],"iteration":39,"passed_time":0.05116537514,"remaining_time":0.07674806272},
{"learn":[5.699603448],"iteration":40,"passed_time":0.0512900227,"remaining_time":0.07380759364},
{"learn":[5.664772458],"iteration":41,"passed_time":0.05140978132,"remaining_time":0.07099445992},
{"learn":[5.6361013],"iteration":42,"passed_time":0.05153706368,"remaining_time":0.06831657279},
{"learn":[5.616379828],"iteration":43,"passed_time":0.051670347,"remaining_time":0.06576225982},
{"learn":[5.595269287],"iteration":44,"passed_time":0.05180218768,"remaining_time":0.06331378494},
{"learn":[5.573092183],"iteration":45,"passed_time":0.05192152554,"remaining_time":0.06095135607},
{"learn":[5.556935857],"iteration":46,"passed_time":0.05204079327,"remaining_time":0.05868429879},
{"learn":[5.54241329],"iteration":47,"passed_time":0.05216242531,"remaining_time":0.05650929409},
{"learn":[5.52043011],"iteration":48,"passed_time":0.05227829684,"remaining_time":0.05441210488},
{"learn":[5.505250587],"iteration":49,"passed_time":0.05239811558,"remaining_time":0.05239811558},
{"learn":[5.48553808],"iteration":50,"passed_time":0.05252845352,"remaining_time":0.05046851416},
{"learn":[5.478474271],"iteration":51,"passed_time":0.05265044622,"remaining_time":0.0486004119},
{"learn":[5.467753795],"iteration":52,"passed_time":0.05276013647,"remaining_time":0.04678729083},
{"learn":[5.454266758],"iteration":53,"passed_time":0.05287750072,"remaining_time":0.04504379691},
{"learn":[5.439733134],"iteration":54,"passed_time":0.05300347069,"remaining_time":0.04336647602},
{"learn":[5.429076645],"iteration":55,"passed_time":0.05313755547,"remaining_time":0.04175093644},
{"learn":[5.422353998],"iteration":56,"passed_time":0.05325591153,"remaining_time":0.04017551221},
{"learn":[5.408016399],"iteration":57,"passed_time":0.05337278489,"remaining_time":0.03864925802},
{"learn":[5.401457932],"iteration":58,"passed_time":0.05350328312,"remaining_time":0.03718024759},
{"learn":[5.392713443],"iteration":59,"passed_time":0.05364478143,"remaining_time":0.03576318762},
{"learn":[5.382189907],"iteration":60,"passed_time":0.05376337794,"remaining_time":0.03437330721},
{"learn":[5.372367709],"iteration":61,"passed_time":0.05388389795,"remaining_time":0.03302561488},
{"learn":[5.367782487],"iteration":62,"passed_time":0.05399861738,"remaining_time":0.0317134737},
{"learn":[5.357320113],"iteration":63,"passed_time":0.05411298617,"remaining_time":0.03043855472},
{"learn":[5.348630505],"iteration":64,"passed_time":0.05425490525,"remaining_time":0.02921417975},
{"learn":[5.342690787],"iteration":65,"passed_time":0.05439151464,"remaining_time":0.02801987118},
{"learn":[5.337130871],"iteration":66,"passed_time":0.05451530061,"remaining_time":0.02685081971},
{"learn":[5.333289715],"iteration":67,"passed_time":0.0546411203,"remaining_time":0.02571346838},
{"learn":[5.322698787],"iteration":68,"passed_time":0.0547718189,"remaining_time":0.02460762878},
{"learn":[5.319060587],"iteration":69,"passed_time":0.05490548291,"remaining_time":0.02353092125},
{"learn":[5.31500939],"iteration":70,"passed_time":0.05502825704,"remaining_time":0.02247633034},
{"learn":[5.308281178],"iteration":71,"passed_time":0.05514791549,"remaining_time":0.02144641158},
{"learn":[5.301244193],"iteration":72,"passed_time":0.05528715968,"remaining_time":0.0204486755},
{"learn":[5.296449558],"iteration":73,"passed_time":0.05542017251,"remaining_time":0.0194719525},
{"learn":[5.29053382],"iteration":74,"passed_time":0.05554375812,"remaining_time":0.01851458604},
{"learn":[5.284581632],"iteration":75,"passed_time":0.05566330636,"remaining_time":0.01757788622},
{"learn":[5.280420773],"iteration":76,"passed_time":0.05579952503,"remaining_time":0.01666739059},
{"learn":[5.276112949],"iteration":77,"passed_time":0.05592737844,"remaining_time":0.01577438879},
{"learn":[5.272546472],"iteration":78,"passed_time":0.05605563257,"remaining_time":0.01490086435},
{"learn":[5.268846318],"iteration":79,"passed_time":0.05619217183,"remaining_time":0.01404804296},
{"learn":[5.265319584],"iteration":80,"passed_time":0.05632321105,"remaining_time":0.01321161741},
{"learn":[5.261823856],"iteration":81,"passed_time":0.05644787864,"remaining_time":0.01239099775},
{"learn":[5.258298819],"iteration":82,"passed_time":0.05657802623,"remaining_time":0.01158827043},
{"learn":[5.249217612],"iteration":83,"passed_time":0.05671545712,"remaining_time":0.01080294421},
{"learn":[5.245746384],"iteration":84,"passed_time":0.05684090613,"remaining_time":0.01003074814},
{"learn":[5.232483579],"iteration":85,"passed_time":0.05696787793,"remaining_time":0.009273840593},
{"learn":[5.227206554],"iteration":86,"passed_time":0.05707833958,"remaining_time":0.008528947293},
{"learn":[5.222898802],"iteration":87,"passed_time":0.05719821842,"remaining_time":0.007799757058},
{"learn":[5.218130945],"iteration":88,"passed_time":0.05731623387,"remaining_time":0.007084028905},
{"learn":[5.215335035],"iteration":89,"passed_time":0.05744975762,"remaining_time":0.006383306403},
{"learn":[5.21138734],"iteration":90,"passed_time":0.05757463559,"remaining_time":0.005694194729},
{"learn":[5.209041943],"iteration":91,"passed_time":0.05768590873,"remaining_time":0.005016165976},
{"learn":[5.205857484],"iteration":92,"passed_time":0.05779807349,"remaining_time":0.004350392628},
{"learn":[5.203748577],"iteration":93,"passed_time":0.05792596697,"remaining_time":0.003697402147},
{"learn":[5.201842679],"iteration":94,"passed_time":0.05805649526,"remaining_time":0.003055605013},
{"learn":[5.194551364],"iteration":95,"passed_time":0.05818231495,"remaining_time":0.002424263123},
{"learn":[5.192112764],"iteration":96,"passed_time":0.05830419745,"remaining_time":0.001803222602},
{"learn":[5.188650623],"iteration":97,"passed_time":0.05842311454,"remaining_time":0.00119230846},
{"learn":[5.185766514],"iteration":98,"passed_time":0.05853836493,"remaining_time":0.0005912966155},
{"learn":[5.183620529],"iteration":99,"passed_time":0.05866040773,"remaining_time":0}
]}